[{"date":{"endDate":{"month":1,"year":1800,"day":3},"startDate":{"month":1,"year":1800,"day":1}},"peopleRelations":{"Mother":"eb6ad4a6-4cba-450d-be0f-baae7d06643b","Father":"eb6ad4a6-4cba-450d-be0f-baae7d06643a"},"placeRelations":{},"name":"Birth","description":"Nascimento do Diogo","specialPurposeFields":{"Maternity":"Bissaya Barreto"},"id":"4de24ac1-f358-4224-8bc3-927be090f62a","type":"Birth","dateRelations":{}},{"date":{"month":9,"hour":2,"year":2000,"day":12,"minute":5,"second":1},"peopleRelations":{"Mother":"eb6ad4a6-4cba-450d-be0f-baae7d06643d","Father":"eb6ad4a6-4cba-450d-be0f-baae7d06643c"},"placeRelations":{},"name":"Birth","description":"Nascimento do Hugo","specialPurposeFields":{"Maternity":"Hospital de Viseu"},"id":"dc1a904f-c091-4cd6-8e71-c7589d3a4a4f","type":"Birth","dateRelations":{}},{"date":{"month":9,"year":2019,"day":12,"minute":5},"peopleRelations":{"Personal Trainer":"eb6ad4a6-4cba-450d-be0f-baae7d06643a"},"placeRelations":{},"name":"Ginásio","description":"Entrada no ginásio","specialPurposeFields":{"Type of Custom Event":"Fitness Hut"},"id":"eb2ef552-0859-4712-a3f0-26defd95246d","type":"CustomEvent","dateRelations":{}},{"date":{"month":9,"year":2103,"day":25,"second":10},"peopleRelations":{"Coveiro":"eb6ad4a6-4cba-450d-be0f-baae7d06643e"},"placeRelations":{},"name":"Death","description":"Morte do Diogo","specialPurposeFields":{"Type of Death":"Death by Age"},"id":"29de8e4b-960a-47ec-a054-968567d4bae1","type":"Death","dateRelations":{}},{"date":{"month":5,"hour":22,"year":2050,"day":25,"minute":15,"second":10},"peopleRelations":{"Motorista":"eb6ad4a6-4cba-450d-be0f-baae7d06643e"},"placeRelations":{},"name":"Emigration","description":"Emigração para Paris","specialPurposeFields":{"Push factor":"Lack of freedom to choose religion, or to choose no religion","Pull factor":"Promise of higher pay","Type of Emigration":"Emigração para Paris"},"id":"7a645f4b-8f8a-4576-8a35-c1ec149087c1","type":"Emigration","dateRelations":{}},{"date":{"month":7,"year":2030,"day":31},"peopleRelations":{"Bride":"eb6ad4a6-4cba-450d-be0f-baae7d06643d"},"placeRelations":{},"name":"Marriage","description":"Casamento realizado em Copa Cabana","specialPurposeFields":{"Type Of Marriage":"Secret marriage","Marriage Name":"Casamento com a Sofia"},"id":"05a8c951-c0af-4fba-a872-1629682c2eaa","type":"Marriage","dateRelations":{}},{"date":{"month":2,"hour":11,"year":2045,"day":18},"peopleRelations":{"Empregado":"eb6ad4a6-4cba-450d-be0f-baae7d06643a"},"placeRelations":{},"name":"Residence","description":"Embaixador do Brasil durante 2 anos","specialPurposeFields":{"Type Of Place":"Villa","Residence Name":"Embaixador do Brasil"},"id":"63297719-2141-4c68-9ab8-120aa89f1939","type":"Residence","dateRelations":{}},{"peopleRelations":{"Partner":"eb6ad4a6-4cba-450d-be0f-baae7d06643f"},"placeRelations":{},"name":"Marriage","description":"aaa","specialPurposeFields":{"Marriage Name":"Casamento a"},"id":"aa1f1a97-a3ed-40d1-a293-fa01ca91c2ee","type":"Marriage","dateRelations":{}},{"peopleRelations":{"Mother":"eb6ad4a6-4cba-450d-be0f-baae7d06643f","Father":"eb6ad4a6-4cba-450d-be0f-baae7d06643e"},"placeRelations":{},"name":"Birth","description":"ooo","specialPurposeFields":{"Maternity":"Nascimento do Legolas"},"id":"57d964f7-316a-43e4-9732-53d6b77b6465","type":"Birth","dateRelations":{}},{"peopleRelations":{"Mother":"eb6ad4a6-4cba-450d-be0f-baae7d06643d","Father":"eb6ad4a6-4cba-450d-be0f-baae7d06643c"},"placeRelations":{},"name":"Birth","description":"mnb","specialPurposeFields":{"Maternity":"Nascimento do Luís"},"id":"8db91629-f472-437d-91d2-706afcbe64a4","type":"Birth","dateRelations":{}}]